{"allow_edit": false, "panes": [{"col_width": 2, "title": "", "width": 1, "widgets": [{"type": "highcharts-timeseries", "settings": {"blocks": 4, "yaxis": "{\"title\":{\"text\" : \"Temperature\"}, \"minorTickInterval\":\"auto\", \"floor\":0}", "series1label": "Temperature", "title": "Temperature", "xaxis": "{\"title\":{\"text\" : \"Time\"}, \"type\": \"datetime\", \"floor\":0}", "timeframe": 60, "chartType": "area", "series1": "datasources[\"zoneData\"][\"temperature\"][\"value\"]"}}, {"type": "highcharts-timeseries", "settings": {"series1": "datasources[\"zoneData\"][\"humidity\"][\"value\"]", "blocks": 4, "yaxis": "{\"title\":{\"text\" : \"Humidity\"}, \"minorTickInterval\":\"auto\", \"floor\":0}", "series1label": "Humidity", "series2label": "", "xaxis": "{\"title\":{\"text\" : \"Time\"}, \"type\": \"datetime\", \"floor\":0}", "timeframe": 60, "series2": "", "title": "Humidity", "chartType": "area"}}], "col": {"3": 1, "2": 1, "4": 2}, "row": {"3": 1, "2": 1, "4": 1}}, {"col_width": 1, "title": "Plant", "width": 1, "widgets": [{"type": "text_widget", "settings": {"animate": true, "size": "regular", "value": "datasources[\"zoneInfo\"][\"plant\"]", "title": ""}}], "col": {"3": 3, "2": 1, "4": 1}, "row": {"3": 1, "2": 19, "4": 1}}, {"widgets": [{"type": "indicator", "settings": {"off_text": "Pump Off", "on_text": "Pump On", "value": "datasources[\"zoneData\"][\"pump\"][\"value\"]", "title": "Pump"}}, {"type": "indicator", "settings": {"title": "Sprinklers", "on_text": "Sprinklers On", "value": "datasources[\"zoneData\"][\"sprinklers\"][\"value\"]", "off_text": "Sprinklers Off"}}, {"type": "indicator", "settings": {"off_text": "Heater Off", "on_text": "Heater On", "value": "datasources[\"zoneData\"][\"heater\"][\"value\"]", "title": "Heater"}}, {"type": "indicator", "settings": {"title": "Cooler", "on_text": "Cooler On", "value": "datasources[\"zoneData\"][\"cooler\"][\"value\"]", "off_text": "Cooler Off"}}, {"type": "indicator", "settings": {"off_text": "Fan Off", "on_text": "Fan On", "value": "datasources[\"zoneData\"][\"fan\"][\"value\"]", "title": "Fan"}}, {"type": "indicator", "settings": {"off_text": "Humidifier Off", "on_text": "Humidifier On", "value": "datasources[\"zoneData\"][\"humidifier\"][\"value\"]", "title": "Humidifier"}}], "width": 1, "col_width": 1, "col": {"3": 3, "2": 1, "4": 4}, "row": {"3": 5, "2": 23, "4": 1}}, {"col_width": 1, "title": "Water Level", "width": 1, "widgets": [{"type": "gauge", "settings": {"units": "%", "max_value": 100, "min_value": 0, "value": "datasources[\"zoneData\"][\"water\"][\"value\"]", "title": ""}}], "col": {"3": 3, "2": 2, "4": 1}, "row": {"3": 17, "2": 19, "4": 5}}], "datasources": [{"type": "JSON", "name": "zoneData", "settings": {"url": "http://192.168.1.4:9090/zone2", "refresh": 1, "use_thingproxy": false, "method": "GET"}}, {"type": "JSON", "name": "zoneInfo", "settings": {"url": "http://192.168.1.4:8080/zones/zone2", "refresh": 2, "use_thingproxy": false, "method": "GET"}}], "version": 1, "plugins": [], "columns": 4}